ez_torch/__init__.py
ez_torch/models.py
ez_torch/tensor_wrapper.py
ez_torch/utils.py
ez_torch-0.1.4.dist-info/WHEEL
ez_torch-0.1.4.dist-info/METADATA
ez_torch-0.1.4.dist-info/RECORD
